acidfile/__init__.py
acidfile_optelgroup-1.2.2.dist-info/LICENSE
acidfile_optelgroup-1.2.2.dist-info/METADATA
acidfile_optelgroup-1.2.2.dist-info/WHEEL
acidfile_optelgroup-1.2.2.dist-info/top_level.txt
acidfile_optelgroup-1.2.2.dist-info/zip-safe
acidfile_optelgroup-1.2.2.dist-info/RECORD
