Metadata-Version: 2.1
Name: acidfile-optelgroup
Version: 1.2.2
Summary: ACID transaction with common files
Home-page: https://gitlab.com/optelgroup-public/acidfile/
Author: Roberto Abdelkader Martínez Pérez, Charles Brunet
Author-email: robertomartinezp@gmail.com, charles.brunet@optelgroup.com
License: LGPLv3
Project-URL: Original Project, https://pypi.org/project/acidfile/
Project-URL: Source, https://gitlab.com/optelgroup-public/acidfile/
Keywords: ACID,transactional file
Platform: UNKNOWN
Classifier: Development Status :: 5 - Production/Stable
Classifier: Intended Audience :: Developers
Classifier: License :: OSI Approved :: GNU Lesser General Public License v3 (LGPLv3)
Classifier: Programming Language :: Python :: 2.7
Classifier: Programming Language :: Python :: 3.6
Classifier: Programming Language :: Python :: 3.7
Classifier: Programming Language :: Python :: 3.8
Classifier: Programming Language :: Python :: 3.9
Classifier: Programming Language :: Python :: 3.10
Classifier: Programming Language :: Python :: Implementation :: PyPy
Classifier: Topic :: Software Development :: Embedded Systems
Classifier: Topic :: System :: Archiving
License-File: LICENSE
